cosinnus_note/__init__.py
cosinnus_note/admin.py
cosinnus_note/apps.py
cosinnus_note/cosinnus_app.py
cosinnus_note/cosinnus_notifications.py
cosinnus_note/dashboard.py
cosinnus_note/filters.py
cosinnus_note/forms.py
cosinnus_note/models.py
cosinnus_note/search_indexes.py
cosinnus_note/urls.py
cosinnus_note/views.py
cosinnus_note/locale/de/LC_MESSAGES/django.mo
cosinnus_note/locale/de/LC_MESSAGES/django.po
cosinnus_note/locale/en/LC_MESSAGES/django.mo
cosinnus_note/locale/en/LC_MESSAGES/django.po
cosinnus_note/locale/fr/LC_MESSAGES/django.mo
cosinnus_note/locale/fr/LC_MESSAGES/django.po
cosinnus_note/locale/ru/LC_MESSAGES/django.mo
cosinnus_note/locale/ru/LC_MESSAGES/django.po
cosinnus_note/locale/uk/LC_MESSAGES/django.mo
cosinnus_note/locale/uk/LC_MESSAGES/django.po
cosinnus_note/migrations/0001_initial.py
cosinnus_note/migrations/0002_auto_20151104_1711.py
cosinnus_note/migrations/0003_auto_20160125_1339.py
cosinnus_note/migrations/0004_auto_20160411_1149.py
cosinnus_note/migrations/__init__.py
cosinnus_note/static/css/note.css
cosinnus_note/templates/cosinnus_note/attached_note.html
cosinnus_note/templates/cosinnus_note/base.html
cosinnus_note/templates/cosinnus_note/note_comments.html
cosinnus_note/templates/cosinnus_note/note_detail.html
cosinnus_note/templates/cosinnus_note/note_embed.html
cosinnus_note/templates/cosinnus_note/note_form.html
cosinnus_note/templates/cosinnus_note/note_form_core.html
cosinnus_note/templates/cosinnus_note/note_form_modal.html
cosinnus_note/templates/cosinnus_note/note_list.html
cosinnus_note/templates/cosinnus_note/note_list_standalone.html
cosinnus_note/templates/cosinnus_note/single_note.html
cosinnus_note/templates/cosinnus_note/single_note_detailed.html
cosinnus_note/templates/cosinnus_note/single_note_embeddable.html
cosinnus_note/templates/cosinnus_note/notifications/note_comment_posted.html
cosinnus_note-0.6.dev20180515152545.dist-info/DESCRIPTION.rst
cosinnus_note-0.6.dev20180515152545.dist-info/METADATA
cosinnus_note-0.6.dev20180515152545.dist-info/RECORD
cosinnus_note-0.6.dev20180515152545.dist-info/WHEEL
cosinnus_note-0.6.dev20180515152545.dist-info/metadata.json
cosinnus_note-0.6.dev20180515152545.dist-info/top_level.txt
